gofetch/__init__.py
gofetch/fetchers/__init__.py
gofetch/fetchers/fetch_shopify.py
gofetch/parsers/__init__.py
gofetch/parsers/parse_shopify.py
gofetch/utils/__init__.py
gofetch/utils/date_utils.py
gofetch/utils/decorator_utils.py
gofetch/utils/nlp_utils.py
gofetch-0.1.5.dist-info/METADATA
gofetch-0.1.5.dist-info/WHEEL
gofetch-0.1.5.dist-info/top_level.txt
gofetch-0.1.5.dist-info/RECORD
